MANIFEST.in
README.rst
setup.py
docs/HISTORY.txt
docs/LICENSE.GPL
docs/LICENSE.txt
simplelayout/__init__.py
simplelayout.portlet.dropzone.egg-info/PKG-INFO
simplelayout.portlet.dropzone.egg-info/SOURCES.txt
simplelayout.portlet.dropzone.egg-info/dependency_links.txt
simplelayout.portlet.dropzone.egg-info/entry_points.txt
simplelayout.portlet.dropzone.egg-info/namespace_packages.txt
simplelayout.portlet.dropzone.egg-info/not-zip-safe
simplelayout.portlet.dropzone.egg-info/requires.txt
simplelayout.portlet.dropzone.egg-info/top_level.txt
simplelayout/portlet/__init__.py
simplelayout/portlet/dropzone/__init__.py
simplelayout/portlet/dropzone/config.py
simplelayout/portlet/dropzone/configure.zcml
simplelayout/portlet/dropzone/interfaces.py
simplelayout/portlet/dropzone/tests.py
simplelayout/portlet/dropzone/update_sl_const.py
simplelayout/portlet/dropzone/browser/__init__.py
simplelayout/portlet/dropzone/browser/configure.zcml
simplelayout/portlet/dropzone/browser/resources/sl-dropzoneportlet.css
simplelayout/portlet/dropzone/configlet/__init__.py
simplelayout/portlet/dropzone/configlet/configure.zcml
simplelayout/portlet/dropzone/configlet/interfaces.py
simplelayout/portlet/dropzone/configlet/view.py
simplelayout/portlet/dropzone/portlets/__init__.py
simplelayout/portlet/dropzone/portlets/configure.zcml
simplelayout/portlet/dropzone/portlets/drop_zone_portlet.pt
simplelayout/portlet/dropzone/portlets/drop_zone_portlet.py
simplelayout/portlet/dropzone/profiles/default/componentregistry.xml
simplelayout/portlet/dropzone/profiles/default/controlpanel.xml
simplelayout/portlet/dropzone/profiles/default/cssregistry.xml
simplelayout/portlet/dropzone/profiles/default/metadata.xml
simplelayout/portlet/dropzone/profiles/default/portlets.xml
simplelayout/portlet/dropzone/profiles/default/viewlets.xml
simplelayout/portlet/dropzone/viewlets/__init__.py
simplelayout/portlet/dropzone/viewlets/configure.zcml
simplelayout/portlet/dropzone/viewlets/listing_portlet.pt
simplelayout/portlet/dropzone/viewlets/viewlets.py