Metadata-Version: 1.0
Name: simplelayout.portlet.dropzone
Version: 1.2.2
Summary: Plone portlet with a simplelayout dropzone.
Home-page: https://github.com/4teamwork/simplelayout.portlet.dropzone
Author: 4teamwork GmbH
Author-email: mailto:info@4teamwork.ch
License: GPL2
Platform: UNKNOWN
Classifier: Framework :: Plone
Classifier: Programming Language :: Python
Classifier: Topic :: Software Development :: Libraries :: Python Modules
